{
    "pools": [
        {
            "rolls": 2,
            "entries": [
                {
                    "type": "loot_table",
                    "name":"gbr:ammo/45acp"
                },
                {
                    "type": "item",
                    "name": "tacz:modern_kinetic_gun",
                    "weight": 1,
                    "functions": [
                        {
                            "function": "set_nbt",
                            "tag": "{GunId:\"tacz:vector45\", GunFireMode:\"AUTO\", HasBulletInBarrel:1b, GunCurrentAmmoCount:26}"
                        }
                    ]
                }
            ]
        }
    ]
}